src/data_mem.v
module data_mem (
    input         clk, rst,
    input  [31:0] addr,
    input  [31:0] data_in,
    input         we,
    input         req,
    output reg [31:0] data_out,
    output reg    ready
);
    reg [31:0] mem [0:255];
    reg [1:0]  delay_count;

    integer i;
    initial begin
        for (i = 0; i < 256; i = i + 1)
            mem[i] = 32'b0;
    end

    always @(posedge clk or posedge rst) begin
        if (rst) begin
            ready       <= 0;
            delay_count <= 0;
            data_out    <= 0;
        end else if (we) begin
            mem[addr[31:2]] <= data_in;
            ready           <= 0;
            delay_count     <= 0;
        end else if (req && !ready) begin
            if (delay_count == 2) begin
                data_out    <= mem[addr[31:2]];
                ready       <= 1;
                delay_count <= 0;
            end else begin
                delay_count <= delay_count + 1;
                ready       <= 0;
            end
        end else if (!req) begin
            ready       <= 0;
            delay_count <= 0;
        end
    end
endmodule

src/dcache.v
module dcache (
    input         clk, rst,
    input  [31:0] addr,
    input  [31:0] data_in,
    input         mem_read,
    input         mem_write,
    output [31:0] data_out,
    output        hit,

    input  [31:0] mem_data,
    input         mem_ready,
    output        mem_req
);
    reg [31:0] cache_data  [0:15];
    reg [25:0] cache_tag   [0:15];
    reg        cache_valid [0:15];

    wire [3:0]  index  = addr[5:2];
    wire [25:0] tag    = addr[31:6];

    wire tag_match = cache_valid[index] && (cache_tag[index] == tag);
    wire read_hit  = mem_read  && tag_match;
    wire write_hit = mem_write && tag_match;

    // stores always proceed, reads need a hit
    assign hit      = mem_write || read_hit;
    assign mem_req  = mem_read && !read_hit;
    assign data_out = mem_write ? data_in : cache_data[index];

    integer i;
    always @(posedge clk or posedge rst) begin
        if (rst) begin
            for (i = 0; i < 16; i = i + 1) begin
                cache_valid[i] <= 0;
                cache_tag[i]   <= 0;
                cache_data[i]  <= 0;
            end
        end else if (mem_write) begin
            cache_data[index]  <= data_in;
            cache_tag[index]   <= tag;
            cache_valid[index] <= 1;
        end else if (mem_read && !read_hit && mem_ready) begin
            cache_data[index]  <= mem_data;
            cache_tag[index]   <= tag;
            cache_valid[index] <= 1;
        end
    end
endmodule

src/alu.v
module alu (
    input  [31:0] a, b,
    input  [3:0]  op,
    output reg [31:0] result,
    output zero
);
    assign zero = (result == 0);

    always @(*) begin
        case (op)
            4'b0000: result = a + b;           // ADD
            4'b0001: result = a - b;           // SUB
            4'b0010: result = a & b;           // AND
            4'b0011: result = a | b;           // OR
            4'b0100: result = a ^ b;           // XOR
            4'b0101: result = a << b[4:0];     // SLL (shift left logical)
            4'b0110: result = a >> b[4:0];     // SRL (shift right logical)
            4'b0111: result = $signed(a) >>> b[4:0]; // SRA (shift right arithmetic)
            4'b1000: result = ($signed(a) < $signed(b)) ? 1 : 0; // SLT (set less than)
            default: result = 32'b0;
        endcase
    end
endmodule

src/forward.v
module forward (
    input  [4:0] idex_rs1, idex_rs2,      // registers needed in EX
    input  [4:0] exmem_rd, memwb_rd,      // destinations in MEM and WB
    input        exmem_reg_write,          // is MEM stage writing?
    input        memwb_reg_write,          // is WB stage writing?
    output reg [1:0] fwd_a, fwd_b         // forwarding selectors
);
    // 00 = use register file output (no forwarding)
    // 01 = forward from MEM/WB
    // 10 = forward from EX/MEM (higher priority — more recent)

    always @(*) begin
        // Forward A (rs1)
        if (exmem_reg_write && exmem_rd != 0 && exmem_rd == idex_rs1)
            fwd_a = 2'b10;  // forward from EX/MEM
        else if (memwb_reg_write && memwb_rd != 0 && memwb_rd == idex_rs1)
            fwd_a = 2'b01;  // forward from MEM/WB
        else
            fwd_a = 2'b00;  // no forwarding needed

        // Forward B (rs2)
        if (exmem_reg_write && exmem_rd != 0 && exmem_rd == idex_rs2)
            fwd_b = 2'b10;
        else if (memwb_reg_write && memwb_rd != 0 && memwb_rd == idex_rs2)
            fwd_b = 2'b01;
        else
            fwd_b = 2'b00;
    end
endmodule

src/imm_decode.v
module imm_decode (
    input  [31:0] instr,
    output reg [31:0] imm
);
    wire [6:0] opcode = instr[6:0];
    always @(*) begin
        case (opcode)
            7'b0010011,
            7'b0000011: imm = {{20{instr[31]}}, instr[31:20]};
            7'b0100011: imm = {{20{instr[31]}}, instr[31:25], instr[11:7]};
            7'b1100011: imm = {{19{instr[31]}}, instr[31], instr[7],
                                instr[30:25], instr[11:8], 1'b0};
            7'b1101111: imm = {{11{instr[31]}}, instr[31], instr[19:12],
                                instr[20], instr[30:21], 1'b0};
            default:    imm = 32'b0;
        endcase
    end
endmodule

src/regfile.v
module regfile (
    input         clk,
    input         we,
    input  [4:0]  rs1, rs2, rd,
    input  [31:0] wd,
    output [31:0] rd1, rd2
);
    reg [31:0] regs [31:0];

    integer i;
    initial begin
        for (i = 0; i < 32; i = i + 1)
            regs[i] = 32'b0;
    end

    assign rd1 = (rs1 == 0) ? 32'b0 : regs[rs1];
    assign rd2 = (rs2 == 0) ? 32'b0 : regs[rs2];

    always @(posedge clk) begin
        if (we && rd != 0)
            regs[rd] <= wd;
    end
endmodule

src/control.v
module control (
    input  [6:0] opcode,
    input  [2:0] funct3,
    input  [6:0] funct7,
    output reg reg_write, alu_src, mem_write, mem_read,
    output reg mem_to_reg, branch, jal,
    output reg [3:0] alu_op
);
    always @(*) begin
        // defaults
        {reg_write, alu_src, mem_write, mem_read,
         mem_to_reg, branch, jal} = 7'b0;
        alu_op = 4'b0000;

        case (opcode)
            7'b0110011: begin // R-type
                reg_write = 1;
                case ({funct7[5], funct3})
                    4'b0000: alu_op = 4'b0000; // ADD
                    4'b1000: alu_op = 4'b0001; // SUB
                    4'b0111: alu_op = 4'b0010; // AND
                    4'b0110: alu_op = 4'b0011; // OR
                    4'b0100: alu_op = 4'b0100; // XOR
                    4'b0001: alu_op = 4'b0101; // SLL
                    4'b0101: alu_op = 4'b0110; // SRL
                    4'b1101: alu_op = 4'b0111; // SRA
                    4'b0010: alu_op = 4'b1000; // SLT
                endcase
            end
            7'b0010011: begin // I-type ALU (addi, andi, etc.)
                reg_write = 1; alu_src = 1;
                case (funct3)
                    3'b000: alu_op = 4'b0000; // ADDI
                    3'b111: alu_op = 4'b0010; // ANDI
                    3'b110: alu_op = 4'b0011; // ORI
                    3'b100: alu_op = 4'b0100; // XORI
                    3'b010: alu_op = 4'b1000; // SLTI
                endcase
            end
            7'b0000011: begin // load (lw)
                reg_write = 1; alu_src = 1;
                mem_read = 1; mem_to_reg = 1;
                alu_op = 4'b0000; // address = base + offset
            end
            7'b0100011: begin // store (sw)
                alu_src = 1; mem_write = 1;
                alu_op = 4'b0000;
            end
            7'b1100011: begin // branch (beq)
                branch = 1;
                alu_op = 4'b0001; // SUB to compare
            end
            7'b1101111: begin // JAL
                reg_write = 1; jal = 1;
            end
        endcase
    end
endmodule

src/main_mem.v
module main_mem (
    input         clk, rst,
    input  [31:0] addr,
    input  [31:0] data_in,
    input         we,
    input         req,
    output reg [31:0] data_out,
    output reg    ready
);
    reg [31:0] mem [0:255];
    reg [1:0]  delay_count;

    initial $readmemh("programs/test.hex", mem);

    always @(posedge clk or posedge rst) begin
        if (rst) begin
            ready       <= 0;
            delay_count <= 0;
            data_out    <= 0;
        end else if (we) begin
            mem[addr[31:2]] <= data_in;
            ready           <= 0;
        end else if (req && !ready) begin
            // start or continue counting toward ready
            if (delay_count == 2) begin
                data_out    <= mem[addr[31:2]];
                ready       <= 1;
                delay_count <= 0;
            end else begin
                delay_count <= delay_count + 1;
                ready       <= 0;
            end
        end else if (!req) begin
            // request dropped — reset
            ready       <= 0;
            delay_count <= 0;
        end
        // if req && ready: hold ready high until req drops
    end
endmodule

src/icache.v
module icache (
    input         clk, rst,
    input  [31:0] addr,
    output [31:0] data_out,
    output        hit,

    input  [31:0] mem_data,
    input         mem_ready,
    output        mem_req
);
    reg [31:0] cache_data  [0:15];
    reg [25:0] cache_tag   [0:15];
    reg        cache_valid [0:15];

    wire [3:0]  index = addr[5:2];
    wire [25:0] tag   = addr[31:6];

    // Combinational hit detection and data output
    assign hit      = cache_valid[index] && (cache_tag[index] == tag);
    assign data_out = cache_data[index];
    assign mem_req  = !hit;

    integer i;
    always @(posedge clk or posedge rst) begin
        if (rst) begin
            for (i = 0; i < 16; i = i + 1) begin
                cache_valid[i] <= 0;
                cache_tag[i]   <= 0;
                cache_data[i]  <= 0;
            end
        end else if (!hit && mem_ready) begin
            cache_data[index]  <= mem_data;
            cache_tag[index]   <= tag;
            cache_valid[index] <= 1;
        end
    end
endmodule

src/hazard.v
module hazard (
    input  [4:0] ifid_rs1, ifid_rs2,   // registers being read in ID
    input  [4:0] idex_rd,              // destination of instruction in EX
    input        idex_mem_read,        // is EX stage a load?
    output reg   stall                 // freeze PC and IF/ID, inject bubble
);
    always @(*) begin
        // Only stall for load-use: instruction in EX is a load AND
        // its destination matches either source of the instruction in ID
        if (idex_mem_read &&
            (idex_rd == ifid_rs1 || idex_rd == ifid_rs2))
            stall = 1;
        else
            stall = 0;
    end
endmodule

src/pipeline_cpu.v
module pipeline_cpu (input clk, input rst);

    // ---- Cache stall signals ----
    wire        icache_hit, dcache_hit;
    wire        icache_mem_req, dcache_mem_req;
    wire [31:0] icache_data_out, dcache_data_out;
    wire [31:0] imem_data_out, dmem_data_out;
    wire        imem_ready, dmem_ready;
    wire        cache_stall;

    assign cache_stall = (!icache_hit) || (exmem_mem_read && !dcache_hit);

    // ---- IF stage wires ----
    reg  [31:0] pc;

    // ---- IF/ID pipeline register ----
    reg [31:0] ifid_instr;
    reg [31:0] ifid_pc;

    // ---- ID stage wires ----
    wire [31:0] rd1_id, rd2_id, imm_id;
    wire        reg_write_id, alu_src_id, mem_write_id;
    wire        mem_read_id, mem_to_reg_id, branch_id, jal_id;
    wire [3:0]  alu_op_id;

    // ---- ID/EX pipeline register ----
    reg [31:0] idex_pc, idex_rd1, idex_rd2, idex_imm;
    reg [4:0]  idex_rs1, idex_rs2, idex_rd;
    reg        idex_reg_write, idex_alu_src, idex_mem_write;
    reg        idex_mem_read, idex_mem_to_reg, idex_branch, idex_jal;
    reg [3:0]  idex_alu_op;

    // ---- EX stage wires ----
    wire [31:0] alu_result_ex;
    wire        zero_ex;
    wire [31:0] branch_target_ex;

    // ---- EX/MEM pipeline register ----
    reg [31:0] exmem_alu_result, exmem_rd2, exmem_pc;
    reg [4:0]  exmem_rd;
    reg        exmem_reg_write, exmem_mem_write;
    reg        exmem_mem_read, exmem_mem_to_reg, exmem_branch, exmem_jal;
    reg        exmem_zero;

    // ---- MEM stage wires ----
    wire [31:0] mem_out_mem;

    // ---- MEM/WB pipeline register ----
    reg [31:0] memwb_alu_result, memwb_mem_out, memwb_pc;
    reg [4:0]  memwb_rd;
    reg        memwb_reg_write, memwb_mem_to_reg, memwb_jal;

    // ---- Performance counters ----
    reg [31:0] cycle_count;
    reg [31:0] icache_miss_count;
    reg [31:0] dcache_miss_count;
    reg        icache_req_prev;   // tracks previous cycle's mem_req to detect rising edge
    reg        exmem_jal_prev;    // tracks previous cycle's jal to suppress wrong-path fetch

    always @(posedge clk or posedge rst) begin
        if (rst) begin
            cycle_count       <= 0;
            icache_miss_count <= 0;
            icache_req_prev   <= 0;
            exmem_jal_prev    <= 0;
            dcache_miss_count <= 0;
        end else begin
            cycle_count     <= cycle_count + 1;
            icache_req_prev <= icache_mem_req;
            exmem_jal_prev  <= exmem_jal;
            if (icache_mem_req && !icache_req_prev && !exmem_jal && !exmem_jal_prev && !(exmem_branch && exmem_zero) && cycle_count > 4)
                icache_miss_count <= icache_miss_count + 1;
            if (dcache_mem_req)
                dcache_miss_count <= dcache_miss_count + 1;
        end
    end

    // ---- Hazard detection unit ----
    wire stall;

    hazard HDU (
        .ifid_rs1(ifid_instr[19:15]),
        .ifid_rs2(ifid_instr[24:20]),
        .idex_rd(idex_rd),
        .idex_mem_read(idex_mem_read),
        .stall(stall)
    );

    // ---- IF stage ----
    icache ICACHE (
        .clk(clk), .rst(rst),
        .addr(pc),
        .data_out(icache_data_out),
        .hit(icache_hit),
        .mem_data(imem_data_out),
        .mem_ready(imem_ready),
        .mem_req(icache_mem_req)
    );

    main_mem IMEM (
        .clk(clk), .rst(rst),
        .addr(pc),
        .data_in(32'b0),
        .we(1'b0),
        .req(icache_mem_req),
        .data_out(imem_data_out),
        .ready(imem_ready)
    );

    always @(posedge clk or posedge rst) begin
        if (rst) begin
            pc         <= 32'b0;
            ifid_instr <= 32'b0;
            ifid_pc    <= 32'b0;
        end else if (exmem_branch && exmem_zero) begin
            pc         <= exmem_pc;
            ifid_instr <= 32'h00000013;
            ifid_pc    <= 32'b0;
        end else if (exmem_jal) begin
            pc         <= exmem_pc;
            ifid_instr <= 32'h00000013;
            ifid_pc    <= 32'b0;
        end else if (stall) begin
            pc         <= pc;
            ifid_instr <= ifid_instr;
            ifid_pc    <= ifid_pc;
        end else if (!cache_stall) begin
            pc         <= pc + 4;
            ifid_instr <= icache_data_out;
            ifid_pc    <= pc;
        end
        // cache miss (icache or dcache): pc and ifid hold
    end

    // ---- ID stage ----
    wire [31:0] write_data_wb;

    control CTRL (
        .opcode(ifid_instr[6:0]), .funct3(ifid_instr[14:12]),
        .funct7(ifid_instr[31:25]),
        .reg_write(reg_write_id), .alu_src(alu_src_id),
        .mem_write(mem_write_id), .mem_read(mem_read_id),
        .mem_to_reg(mem_to_reg_id), .branch(branch_id),
        .jal(jal_id), .alu_op(alu_op_id)
    );

    regfile RF (
        .clk(clk),
        .we(memwb_reg_write),
        .rs1(ifid_instr[19:15]),
        .rs2(ifid_instr[24:20]),
        .rd(memwb_rd),
        .wd(write_data_wb),
        .rd1(rd1_id), .rd2(rd2_id)
    );

    imm_decode IMM (.instr(ifid_instr), .imm(imm_id));

    always @(posedge clk or posedge rst) begin
        if (rst) begin
            idex_pc <= 0; idex_rd1 <= 0; idex_rd2 <= 0; idex_imm <= 0;
            idex_rs1 <= 0; idex_rs2 <= 0; idex_rd <= 0;
            idex_reg_write <= 0; idex_alu_src <= 0; idex_mem_write <= 0;
            idex_mem_read <= 0; idex_mem_to_reg <= 0;
            idex_branch <= 0; idex_jal <= 0; idex_alu_op <= 0;
        end else if (cache_stall) begin
            idex_pc <= idex_pc; idex_rd1 <= idex_rd1; idex_rd2 <= idex_rd2;
            idex_imm <= idex_imm; idex_rs1 <= idex_rs1; idex_rs2 <= idex_rs2;
            idex_rd <= idex_rd; idex_reg_write <= idex_reg_write;
            idex_alu_src <= idex_alu_src; idex_mem_write <= idex_mem_write;
            idex_mem_read <= idex_mem_read; idex_mem_to_reg <= idex_mem_to_reg;
            idex_branch <= idex_branch; idex_jal <= idex_jal;
            idex_alu_op <= idex_alu_op;
        end else if (stall || (exmem_branch && exmem_zero) || exmem_jal) begin
            idex_pc <= 0; idex_rd1 <= 0; idex_rd2 <= 0; idex_imm <= 0;
            idex_rs1 <= 0; idex_rs2 <= 0; idex_rd <= 0;
            idex_reg_write <= 0; idex_alu_src <= 0; idex_mem_write <= 0;
            idex_mem_read <= 0; idex_mem_to_reg <= 0;
            idex_branch <= 0; idex_jal <= 0; idex_alu_op <= 0;
        end else begin
            idex_pc         <= ifid_pc;
            idex_rd1        <= rd1_id;
            idex_rd2        <= rd2_id;
            idex_imm        <= imm_id;
            idex_rs1        <= ifid_instr[19:15];
            idex_rs2        <= ifid_instr[24:20];
            idex_rd         <= ifid_instr[11:7];
            idex_reg_write  <= reg_write_id;
            idex_alu_src    <= alu_src_id;
            idex_mem_write  <= mem_write_id;
            idex_mem_read   <= mem_read_id;
            idex_mem_to_reg <= mem_to_reg_id;
            idex_branch     <= branch_id;
            idex_jal        <= jal_id;
            idex_alu_op     <= alu_op_id;
        end
    end

    // ---- EX stage ----
    wire [1:0] fwd_a, fwd_b;

    forward FWD (
        .idex_rs1(idex_rs1), .idex_rs2(idex_rs2),
        .exmem_rd(exmem_rd), .memwb_rd(memwb_rd),
        .exmem_reg_write(exmem_reg_write),
        .memwb_reg_write(memwb_reg_write),
        .fwd_a(fwd_a), .fwd_b(fwd_b)
    );

    wire [31:0] alu_a_ex, alu_b_pre, alu_b_ex;

    assign alu_a_ex = (fwd_a == 2'b10) ? exmem_alu_result :
                      (fwd_a == 2'b01) ? write_data_wb    :
                                         idex_rd1;

    assign alu_b_pre = (fwd_b == 2'b10) ? exmem_alu_result :
                       (fwd_b == 2'b01) ? write_data_wb    :
                                          idex_rd2;

    assign alu_b_ex = idex_alu_src ? idex_imm : alu_b_pre;

    assign branch_target_ex = idex_pc + idex_imm;

    alu ALU (
        .a(alu_a_ex), .b(alu_b_ex),
        .op(idex_alu_op),
        .result(alu_result_ex), .zero(zero_ex)
    );

    always @(posedge clk or posedge rst) begin
        if (rst) begin
            exmem_alu_result <= 0; exmem_rd2 <= 0; exmem_pc <= 0;
            exmem_rd <= 0; exmem_reg_write <= 0; exmem_mem_write <= 0;
            exmem_mem_read <= 0; exmem_mem_to_reg <= 0;
            exmem_branch <= 0; exmem_jal <= 0; exmem_zero <= 0;
        end else if (cache_stall) begin
            exmem_alu_result <= exmem_alu_result; exmem_rd2 <= exmem_rd2;
            exmem_pc <= exmem_pc; exmem_rd <= exmem_rd;
            exmem_reg_write <= exmem_reg_write;
            exmem_mem_write <= exmem_mem_write;
            exmem_mem_read <= exmem_mem_read;
            exmem_mem_to_reg <= exmem_mem_to_reg;
            exmem_branch <= exmem_branch; exmem_jal <= exmem_jal;
            exmem_zero <= exmem_zero;
        end else begin
            exmem_alu_result <= alu_result_ex;
            exmem_rd2        <= alu_b_pre;
            exmem_pc         <= branch_target_ex;
            exmem_rd         <= idex_rd;
            exmem_reg_write  <= idex_reg_write;
            exmem_mem_write  <= idex_mem_write;
            exmem_mem_read   <= idex_mem_read;
            exmem_mem_to_reg <= idex_mem_to_reg;
            exmem_branch     <= idex_branch;
            exmem_jal        <= idex_jal;
            exmem_zero       <= zero_ex;
        end
    end

    // ---- MEM stage ----
    dcache DCACHE (
        .clk(clk), .rst(rst),
        .addr(exmem_alu_result),
        .data_in(exmem_rd2),
        .mem_read(exmem_mem_read),
        .mem_write(exmem_mem_write),
        .data_out(dcache_data_out),
        .hit(dcache_hit),
        .mem_data(dmem_data_out),
        .mem_ready(dmem_ready),
        .mem_req(dcache_mem_req)
    );

    data_mem DMEM (
        .clk(clk), .rst(rst),
        .addr(exmem_alu_result),
        .data_in(exmem_rd2),
        .we(exmem_mem_write),
        .req(dcache_mem_req),
        .data_out(dmem_data_out),
        .ready(dmem_ready)
    );

    assign mem_out_mem = dcache_data_out;

    always @(posedge clk or posedge rst) begin
        if (rst) begin
            memwb_alu_result <= 0; memwb_mem_out <= 0; memwb_pc <= 0;
            memwb_rd <= 0; memwb_reg_write <= 0;
            memwb_mem_to_reg <= 0; memwb_jal <= 0;
        end else if (cache_stall) begin
            memwb_alu_result <= memwb_alu_result;
            memwb_mem_out <= memwb_mem_out;
            memwb_pc <= memwb_pc; memwb_rd <= memwb_rd;
            memwb_reg_write <= memwb_reg_write;
            memwb_mem_to_reg <= memwb_mem_to_reg;
            memwb_jal <= memwb_jal;
        end else begin
            memwb_alu_result <= exmem_alu_result;
            memwb_mem_out    <= mem_out_mem;
            memwb_pc         <= exmem_pc + 4;
            memwb_rd         <= exmem_rd;
            memwb_reg_write  <= exmem_reg_write;
            memwb_mem_to_reg <= exmem_mem_to_reg;
            memwb_jal        <= exmem_jal;
        end
    end

    // ---- WB stage ----
    assign write_data_wb = memwb_jal        ? memwb_pc :
                           memwb_mem_to_reg ? memwb_mem_out :
                                              memwb_alu_result;

endmodule

cpu_tb_debug.v
module cpu_tb;
    reg clk, rst;
    pipeline_cpu DUT (.clk(clk), .rst(rst));

    initial clk = 0;
    always #5 clk = ~clk;

    always @(posedge clk) begin
        if (!rst) begin
            if (DUT.icache_mem_req && !DUT.icache_req_prev && !DUT.exmem_jal && !DUT.exmem_jal_prev && !(DUT.exmem_branch && DUT.exmem_zero) && DUT.cycle_count > 4)
                $display("MISS_COUNT cy=%0d pc=%08h imem_req=%0d exmem_jal=%0d exmem_jal_prev=%0d", DUT.cycle_count, DUT.pc, DUT.icache_mem_req, DUT.exmem_jal, DUT.exmem_jal_prev);
            $display("CY=%0d PC=%08h WBrd=%0d WBdata=%08h WBwe=%0d exmem_memw=%0d exmem_memr=%0d exmem_rd2=%08h dcache_hit=%0d",
                DUT.cycle_count, DUT.pc,
                DUT.memwb_rd, DUT.write_data_wb, DUT.memwb_reg_write,
                DUT.exmem_mem_write, DUT.exmem_mem_read,
                DUT.exmem_rd2, DUT.dcache_hit);
        end
    end

    initial begin
        $dumpfile("cpu.vcd");
        $dumpvars(0, cpu_tb);
        rst = 1; #15; rst = 0;
        #5000;
        $display("FINAL: cycles=%0d imiss=%0d dmiss=%0d",
                 DUT.cycle_count,
                 DUT.icache_miss_count,
                 DUT.dcache_miss_count);
        $finish;
    end
endmodule

cpu.vcd
$date
	Fri May 29 20:58:50 2026
$end
$version
	Icarus Verilog
$end
$timescale
	1s
$end
$scope module cpu_tb $end
$var reg 1 ! clk $end
$var reg 1 " rst $end
$scope module DUT $end
$var wire 1 # cache_stall $end
$var wire 1 ! clk $end
$var wire 32 $ mem_out_mem [31:0] $end
$var wire 1 " rst $end
$var wire 1 % zero_ex $end
$var wire 32 & write_data_wb [31:0] $end
$var wire 1 ' stall $end
$var wire 1 ( reg_write_id $end
$var wire 32 ) rd2_id [31:0] $end
$var wire 32 * rd1_id [31:0] $end
$var wire 1 + mem_write_id $end
$var wire 1 , mem_to_reg_id $end
$var wire 1 - mem_read_id $end
$var wire 1 . jal_id $end
$var wire 32 / imm_id [31:0] $end
$var wire 1 0 imem_ready $end
$var wire 32 1 imem_data_out [31:0] $end
$var wire 1 2 icache_mem_req $end
$var wire 1 3 icache_hit $end
$var wire 32 4 icache_data_out [31:0] $end
$var wire 2 5 fwd_b [1:0] $end
$var wire 2 6 fwd_a [1:0] $end
$var wire 1 7 dmem_ready $end
$var wire 32 8 dmem_data_out [31:0] $end
$var wire 1 9 dcache_mem_req $end
$var wire 1 : dcache_hit $end
$var wire 32 ; dcache_data_out [31:0] $end
$var wire 32 < branch_target_ex [31:0] $end
$var wire 1 = branch_id $end
$var wire 1 > alu_src_id $end
$var wire 32 ? alu_result_ex [31:0] $end
$var wire 4 @ alu_op_id [3:0] $end
$var wire 32 A alu_b_pre [31:0] $end
$var wire 32 B alu_b_ex [31:0] $end
$var wire 32 C alu_a_ex [31:0] $end
$var reg 32 D cycle_count [31:0] $end
$var reg 32 E dcache_miss_count [31:0] $end
$var reg 32 F exmem_alu_result [31:0] $end
$var reg 1 G exmem_branch $end
$var reg 1 H exmem_jal $end
$var reg 1 I exmem_jal_prev $end
$var reg 1 J exmem_mem_read $end
$var reg 1 K exmem_mem_to_reg $end
$var reg 1 L exmem_mem_write $end
$var reg 32 M exmem_pc [31:0] $end
$var reg 5 N exmem_rd [4:0] $end
$var reg 32 O exmem_rd2 [31:0] $end
$var reg 1 P exmem_reg_write $end
$var reg 1 Q exmem_zero $end
$var reg 32 R icache_miss_count [31:0] $end
$var reg 1 S icache_req_prev $end
$var reg 4 T idex_alu_op [3:0] $end
$var reg 1 U idex_alu_src $end
$var reg 1 V idex_branch $end
$var reg 32 W idex_imm [31:0] $end
$var reg 1 X idex_jal $end
$var reg 1 Y idex_mem_read $end
$var reg 1 Z idex_mem_to_reg $end
$var reg 1 [ idex_mem_write $end
$var reg 32 \ idex_pc [31:0] $end
$var reg 5 ] idex_rd [4:0] $end
$var reg 32 ^ idex_rd1 [31:0] $end
$var reg 32 _ idex_rd2 [31:0] $end
$var reg 1 ` idex_reg_write $end
$var reg 5 a idex_rs1 [4:0] $end
$var reg 5 b idex_rs2 [4:0] $end
$var reg 32 c ifid_instr [31:0] $end
$var reg 32 d ifid_pc [31:0] $end
$var reg 32 e memwb_alu_result [31:0] $end
$var reg 1 f memwb_jal $end
$var reg 32 g memwb_mem_out [31:0] $end
$var reg 1 h memwb_mem_to_reg $end
$var reg 32 i memwb_pc [31:0] $end
$var reg 5 j memwb_rd [4:0] $end
$var reg 1 k memwb_reg_write $end
$var reg 32 l pc [31:0] $end
$scope module ALU $end
$var wire 32 m a [31:0] $end
$var wire 32 n b [31:0] $end
$var wire 4 o op [3:0] $end
$var wire 1 % zero $end
$var reg 32 p result [31:0] $end
$upscope $end
$scope module CTRL $end
$var wire 3 q funct3 [2:0] $end
$var wire 7 r funct7 [6:0] $end
$var wire 7 s opcode [6:0] $end
$var reg 4 t alu_op [3:0] $end
$var reg 1 > alu_src $end
$var reg 1 = branch $end
$var reg 1 . jal $end
$var reg 1 - mem_read $end
$var reg 1 , mem_to_reg $end
$var reg 1 + mem_write $end
$var reg 1 ( reg_write $end
$upscope $end
$scope module DCACHE $end
$var wire 32 u addr [31:0] $end
$var wire 1 ! clk $end
$var wire 32 v data_in [31:0] $end
$var wire 1 : hit $end
$var wire 1 J mem_read $end
$var wire 1 9 mem_req $end
$var wire 1 L mem_write $end
$var wire 1 w read_hit $end
$var wire 1 " rst $end
$var wire 1 x tag_match $end
$var wire 1 y write_hit $end
$var wire 26 z tag [25:0] $end
$var wire 1 7 mem_ready $end
$var wire 32 { mem_data [31:0] $end
$var wire 4 | index [3:0] $end
$var wire 32 } data_out [31:0] $end
$var integer 32 ~ i [31:0] $end
$upscope $end
$scope module DMEM $end
$var wire 32 !" addr [31:0] $end
$var wire 1 ! clk $end
$var wire 32 "" data_in [31:0] $end
$var wire 1 9 req $end
$var wire 1 " rst $end
$var wire 1 L we $end
$var reg 32 #" data_out [31:0] $end
$var reg 2 $" delay_count [1:0] $end
$var reg 1 7 ready $end
$var integer 32 %" i [31:0] $end
$upscope $end
$scope module FWD $end
$var wire 5 &" exmem_rd [4:0] $end
$var wire 1 P exmem_reg_write $end
$var wire 5 '" idex_rs1 [4:0] $end
$var wire 5 (" idex_rs2 [4:0] $end
$var wire 5 )" memwb_rd [4:0] $end
$var wire 1 k memwb_reg_write $end
$var reg 2 *" fwd_a [1:0] $end
$var reg 2 +" fwd_b [1:0] $end
$upscope $end
$scope module HDU $end
$var wire 1 Y idex_mem_read $end
$var wire 5 ," idex_rd [4:0] $end
$var wire 5 -" ifid_rs1 [4:0] $end
$var wire 5 ." ifid_rs2 [4:0] $end
$var reg 1 ' stall $end
$upscope $end
$scope module ICACHE $end
$var wire 32 /" addr [31:0] $end
$var wire 1 ! clk $end
$var wire 32 0" data_out [31:0] $end
$var wire 1 3 hit $end
$var wire 1 " rst $end
$var wire 26 1" tag [25:0] $end
$var wire 1 2 mem_req $end
$var wire 1 0 mem_ready $end
$var wire 32 2" mem_data [31:0] $end
$var wire 4 3" index [3:0] $end
$var integer 32 4" i [31:0] $end
$upscope $end
$scope module IMEM $end
$var wire 32 5" addr [31:0] $end
$var wire 1 ! clk $end
$var wire 32 6" data_in [31:0] $end
$var wire 1 2 req $end
$var wire 1 " rst $end
$var wire 1 7" we $end
$var reg 32 8" data_out [31:0] $end
$var reg 2 9" delay_count [1:0] $end
$var reg 1 0 ready $end
$upscope $end
$scope module IMM $end
$var wire 32 :" instr [31:0] $end
$var wire 7 ;" opcode [6:0] $end
$var reg 32 <" imm [31:0] $end
$upscope $end
$scope module RF $end
$var wire 1 ! clk $end
$var wire 5 =" rd [4:0] $end
$var wire 5 >" rs1 [4:0] $end
$var wire 5 ?" rs2 [4:0] $end
$var wire 32 @" wd [31:0] $end
$var wire 1 k we $end
$var wire 32 A" rd2 [31:0] $end
$var wire 32 B" rd1 [31:0] $end
$var integer 32 C" i [31:0] $end
$upscope $end
$upscope $end
$upscope $end
$enddefinitions $end
$comment Show the parameter values. $end
$dumpall
$end
#0
$dumpvars
b100000 C"
b0 B"
b0 A"
b0 @"
b0 ?"
b0 >"
b0 ="
b0 <"
b0 ;"
b0 :"
b0 9"
b0 8"
07"
b0 6"
b0 5"
b10000 4"
b0 3"
b0 2"
b0 1"
b0 0"
b0 /"
b0 ."
b0 -"
b0 ,"
b0 +"
b0 *"
b0 )"
b0 ("
b0 '"
b0 &"
b100000000 %"
b0 $"
b0 #"
b0 ""
b0 !"
b10000 ~
b0 }
b0 |
b0 {
b0 z
0y
0x
0w
b0 v
b0 u
b0 t
b0 s
b0 r
b0 q
b0 p
b0 o
b0 n
b0 m
b0 l
0k
b0 j
b0 i
0h
b0 g
0f
b0 e
b0 d
b0 c
b0 b
b0 a
0`
b0 _
b0 ^
b0 ]
b0 \
0[
0Z
0Y
0X
b0 W
0V
0U
b0 T
0S
b0 R
0Q
0P
b0 O
b0 N
b0 M
0L
0K
0J
0I
0H
0G
b0 F
b0 E
b0 D
b0 C
b0 B
b0 A
b0 @
b0 ?
0>
0=
b0 <
b0 ;
0:
09
b0 8
07
b0 6
b0 5
b0 4
03
12
b0 1
00
b0 /
0.
0-
0,
0+
b0 *
b0 )
0(
0'
b0 &
1%
b0 $
1#
1"
0!
$end
#5
b10000 ~
b10000 4"
1!
#10
0!
#15
b1 9"
1S
b1 D
1!
0"
#20
0!
#25
b10 D
b10 9"
1!
#30
0!
#35
b0 9"
10
b10100000000000010010011 1
b10100000000000010010011 2"
b10100000000000010010011 8"
b11 D
1!
#40
0!
#45
0#
02
13
b100 D
b10100000000000010010011 4
b10100000000000010010011 0"
1!
#50
0!
#55
1#
1>
1(
12
03
b101 ."
b10011 s
b101 ?"
b101 /
b101 <"
b10011 ;"
b0 4
b0 0"
b1 3"
00
0S
b101 D
b10100000000000010010011 c
b10100000000000010010011 :"
b100 l
b100 /"
b100 5"
1Q
b100 i
1!
#60
0!
#65
b1 R
1S
b110 D
b1 9"
1!
#70
0!
#75
b10 9"
b111 D
1!
#80
0!
#85
b1000 D
b0 9"
10
b101000000000000100010011 1
b101000000000000100010011 2"
b101000000000000100010011 8"
1!
#90
0!
#95
0#
02
13
b101000000000000100010011 4
b101000000000000100010011 0"
b1001 D
1!
#100
0!
